setup.cfg
setup.py
pytinypng/__init__.py
pytinypng/api.py
pytinypng/domain.py
pytinypng/handlers.py
pytinypng/pytinypng.py
pytinypng/utils.py
pytinypng.egg-info/PKG-INFO
pytinypng.egg-info/SOURCES.txt
pytinypng.egg-info/dependency_links.txt
pytinypng.egg-info/entry_points.txt
pytinypng.egg-info/top_level.txt