Metadata-Version: 1.1
Name: pytinypng
Version: 0.0.9
Summary: Batch compression for PNG images
Home-page: https://github.com/vasilcovsky/pytinypng
Author: Igor Vasilcovsky
Author-email: vasilcovsky@gmail.com
License: BSD License
Keywords: tinyping compression png optimization
Platform: UNKNOWN
Classifier: Development Status :: 3 - Alpha
Classifier: Environment :: Console
Classifier: Intended Audience :: Developers
Classifier: License :: OSI Approved :: BSD License
Classifier: Topic :: System :: Archiving :: Compression
